{
  "api": {
    "trainler": {
      "dependsOn": [
        {
          "attributes": [
            "UserPoolId"
          ],
          "category": "auth",
          "resourceName": "trainler1dd9b1e9"
        }
      ],
      "output": {
        "authConfig": {
          "additionalAuthenticationProviders": [
            {
              "apiKeyConfig": {
                "apiKeyExpirationDate": "2026-01-01T00:45:22.688Z",
                "apiKeyExpirationDays": 365,
                "description": ""
              },
              "authenticationType": "API_KEY"
            }
          ],
          "defaultAuthentication": {
            "authenticationType": "AMAZON_COGNITO_USER_POOLS",
            "userPoolConfig": {
              "userPoolId": "authtrainler1dd9b1e9"
            }
          }
        }
      },
      "providerPlugin": "awscloudformation",
      "service": "AppSync"
    }
  },
  "auth": {
    "trainler1dd9b1e9": {
      "customAuth": false,
      "dependsOn": [],
      "frontendAuthConfig": {
        "mfaConfiguration": "OFF",
        "mfaTypes": [
          "SMS"
        ],
        "passwordProtectionSettings": {
          "passwordPolicyCharacters": [],
          "passwordPolicyMinLength": 8
        },
        "signupAttributes": [
          "EMAIL"
        ],
        "socialProviders": [],
        "usernameAttributes": [
          "EMAIL"
        ],
        "verificationMechanisms": [
          "EMAIL"
        ]
      },
      "providerPlugin": "awscloudformation",
      "service": "Cognito"
    },
    "userPoolGroups": {
      "dependsOn": [
        {
          "attributes": [
            "UserPoolId",
            "AppClientIDWeb",
            "AppClientID",
            "IdentityPoolId"
          ],
          "category": "auth",
          "resourceName": "trainler1dd9b1e9"
        }
      ],
      "providerPlugin": "awscloudformation",
      "service": "Cognito-UserPool-Groups"
    }
  }
}